LICENSE
MANIFEST.in
Makefile
README.md
pyproject.toml
setup.py
pywgsim/__init__.py
pywgsim/__main__.py
pywgsim/main.py
pywgsim/wgsim_lib.c
pywgsim/wgsim_lib.pyx
pywgsim.egg-info/PKG-INFO
pywgsim.egg-info/SOURCES.txt
pywgsim.egg-info/dependency_links.txt
pywgsim.egg-info/entry_points.txt
pywgsim.egg-info/requires.txt
pywgsim.egg-info/top_level.txt
pywgsim/src/kseq.h
pywgsim/src/wgsim_mod.c
pywgsim/src/wgsim_mod.h
scripts/eval.sh
scripts/pywgsim-Darwin
scripts/pywgsim-Linux
scripts/pywgsim.py
test/test.py