Metadata-Version: 2.4
Name: pywgsim
Version: 0.6.0
Summary: pywgsim
Home-page: https://github.com/ialbert/pywgsim
Author: Istvan Albert
Author-email: istvan.albert@gmail.com
Classifier: Programming Language :: Python :: 3
Classifier: License :: OSI Approved :: MIT License
Classifier: Operating System :: POSIX
Classifier: Programming Language :: C
Classifier: Programming Language :: Cython
Requires-Python: >=3.6
License-File: LICENSE
Requires-Dist: plac
Dynamic: author
Dynamic: author-email
Dynamic: classifier
Dynamic: description
Dynamic: description-content-type
Dynamic: home-page
Dynamic: license-file
Dynamic: requires-dist
Dynamic: requires-python
Dynamic: summary
